[{
        "userName": "GW",
        "time": -1,
        "text": "Good techniques used here...",
        "type": "appreciation",
        "contentPosition": "none",
        "commentId": "t1"
    }, {
        "userName": "H",
        "time": -1,
        "text": "Hey thanks Graham! I'm always looking for ideas for new tutorials!",
        "type": "appreciation",
        "contentPosition": "none",
        "commentId": "t2"
    }, {
        "userName": "GW",
        "time": -1,
        "text": "I just spent the weekend editing a series of composite layered images and you showed me two tricks I could have used during that process, I always enjoy seeing vids like this, thanks Mike!!",
        "type": "appreciation",
        "contentPosition": "none",
        "commentId": "t3"
    }, {
        "userName": "H",
        "time": -1,
        "text": "My pleasure! stop by any time!",
        "type": "appreciation",
        "contentPosition": "none",
        "commentId": "t4"
    }, {
        "userName": "JB",
        "time": -1,
        "text": "Constantly watching this editing photos for GCSE Photography. I've managed to get some pretty cool ideas out of this.. Thanks. Please reply with any other videos that I can use to Photoshop some creative photos for my GCSE's, thanks again!",
        "type": "appreciation",
        "contentPosition": "none",
        "commentId": "t5"
    }, {
        "userName": "H",
        "time": -1,
        "text": "Check out the rest of my channel for more videos! Also if you have any ideas for videos you'd like to see drop me a line and I will try to make them!",
        "type": "appreciation",
        "contentPosition": "none",
        "commentId": "t6"
    }, {
        "userName": "P",
        "time": -1,
        "text": "Thank you! You're a great teacher.",
        "type": "appreciation",
        "contentPosition": "none",
        "commentId": "t7"
    }, {
        "userName": "H",
        "time": -1,
        "text": "Thanks so much for dropping by to check my stuff out!",
        "type": "appreciation",
        "contentPosition": "none",
        "commentId": "t8"
    }, {
        "userName": "MS",
        "time": -1,
        "text": "Great job! Hope I can do something like that! THANX!!",
        "type": "appreciation",
        "contentPosition": "none",
        "commentId": "t9"
    }, {
        "userName": "H",
        "time": -1,
        "text": "Thanks for checking it out, I hope it helps!",
        "type": "appreciation",
        "contentPosition": "none",
        "commentId": "t10"
    }, {
        "userName": "EP",
        "time": -1,
        "text": "Thanks",
        "type": "appreciation",
        "contentPosition": "none",
        "commentId": "t11"
    }, {
        "userName": "H",
        "time": -1,
        "text": "Thanks for checking out my video!",
        "type": "appreciation",
        "contentPosition": "none",
        "commentId": "t12"
    }, {
        "userName": "E",
        "time": -1,
        "text": "Awesome. I'll give that a try!",
        "type": "appreciation",
        "contentPosition": "none",
        "commentId": "t13"
    }, {
        "userName": "R",
        "time": -1,
        "text": "Thank you Mike. Nice and easy to understand. No annoying rock music in the background overplaying your voice. Good work.",
        "type": "appreciation",
        "contentPosition": "none",
        "commentId": "t14"
    }, {
        "userName": "H",
        "time": -1,
        "text": "Thank you for watching!",
        "type": "appreciation",
        "contentPosition": "none",
        "commentId": "t15"
    }, {
        "userName": "B",
        "time": -1,
        "text": "Thanks are the best?",
        "type": "appreciation",
        "contentPosition": "none",
        "commentId": "t16"
    }, {
        "userName": "SE",
        "time": -1,
        "text": " Hi Mike, I'm just starting out with Photoshop and your tutorial is brilliant! You explain so clearly every step of the process - even what controls to use, brush size etc and don't take the simplest things for granted eg that someone knows how to copy one image onto another. Will definitely watch out for more and have just subscribed to your channel. Thanks a million!??",
        "type": "appreciation",
        "contentPosition": "none",
        "commentId": "t17"
    }, {
        "userName": "H",
        "time": -1,
        "text": "Thank you so much for checking out my videos and I'm really glad you enjoyed this one!  Feel free to send me ideas for new tutorials.",
        "type": "appreciation",
        "contentPosition": "none",
        "commentId": "t18"
    }, {
        "userName": "6A",
        "time": -1,
        "text": "AWESOME! Thank you so much!?",
        "type": "appreciation",
        "contentPosition": "none",
        "commentId": "t19"
    }, {
        "userName": "O",
        "time": -1,
        "text": "Mike...you are true Photoshop Expert and Instructor!you explained so clear and precise, no one could do better !thank you so much...Master!!?",
        "type": "appreciation",
        "contentPosition": "none",
        "commentId": "t20"
    }, {
        "userName": "H",
        "time": -1,
        "text": "Thank you so much for checking it out!  I'm always looking for ideas to do more tutorials and would love your input!Thanks again!!?",
        "type": "appreciation",
        "contentPosition": "none",
        "commentId": "t21"
    }, {
        "userName": "AY",
        "time": -1,
        "text": "thank you so much! this helped me out a lot :D??",
        "type": "appreciation",
        "contentPosition": "none",
        "commentId": "t22"
    }, {
        "userName": "0",
        "time": -1,
        "text": "hello there first time watching your tutorials nice and easy to understand and with your video i achieved what i wanted with my image thank you",
        "type": "appreciation",
        "contentPosition": "none",
        "commentId": "t23"
    }, {
        "userName": "AH",
        "time": 209,
        "text": "Hello. When I go to paint the face (after following the steps in the video). The face begins to be erased, and its the background that can be painted black. Have I missed a step some where along the line? I enjoy the video it is easy to follow except I am missing something. Thanks in advance???",
        "type": "troubleshooting",
        "contentPosition": "none",
        "commentId": "t24"
    }, {
        "userName": "KB",
        "time": 23,
        "text": "how do you open the next photo?",
        "type": "question",
        "contentPosition": "none",
        "commentId": "t26"
    }, {
        "userName": "L",
        "time": 23,
        "text": "How can I open two photos at the same time ??",
        "type": "question",
        "contentPosition": "none",
        "commentId": "t27"
    }, {
        "userName": "M",
        "time": -1,
        "text": "THX",
        "type": "appreciation",
        "contentPosition": "none",
        "commentId": "t28"
    }, {
        "userName": "B",
        "time": -1,
        "text": "very helpful thank you!",
        "type": "appreciation",
        "contentPosition": "none",
        "commentId": "t29"
    }, {
        "userName": "RP",
        "time": -1,
        "text": "Thanks",
        "type": "appreciation",
        "contentPosition": "none",
        "commentId": "t30"
    }, {
        "userName": "KG",
        "time": -1,
        "text": "Thx!",
        "type": "appreciation",
        "contentPosition": "none",
        "commentId": "t31"
    }, {
        "userName": "IM",
        "time": -1,
        "text": "LOL THX I WAS LIKE ANGRY I COULDNT DO THAT",
        "type": "appreciation",
        "contentPosition": "none",
        "commentId": "t32"
    }, {
        "userName": "ZM",
        "time": -1,
        "text": "That was awesome! Thank you!",
        "type": "appreciation",
        "contentPosition": "none",
        "commentId": "t33"
    }, {
        "userName": "S",
        "time": -1,
        "text": "Thank you. You are a great teacher. Nice clear voice and easy to follow  images.",
        "type": "appreciation",
        "contentPosition": "none",
        "commentId": "t34"
    }, {
        "userName": "OA",
        "time": -1,
        "text": "thx!",
        "type": "appreciation",
        "contentPosition": "none",
        "commentId": "t35"
    }, {
        "userName": "NT",
        "time": -1,
        "text": "You have a natural talent in teaching!",
        "type": "appreciation",
        "contentPosition": "none",
        "commentId": "t36"
    }, {
        "userName": "F",
        "time": 248,
        "text": "Im sry i don't speak English a lot can you tell me what you said at 4:08 click control and what? Tnx",
        "type": "question",
        "contentPosition": "none",
        "commentId": "t37"
    }, {
        "userName": "1",
        "time": -1,
        "text": "thank you so much for this video, I've been trying to find any info for  hours on how to do this!!﻿",
        "type": "appreciation",
        "contentPosition": "none",
        "commentId": "t38"
    }, {
        "userName": "RM",
        "time": -1,
        "text": "Thanks.",
        "type": "appreciation",
        "contentPosition": "none",
        "commentId": "t39"
    }, {
        "userName": "W",
        "time": -1,
        "text": "Thank you Mike \"from Hebdon photography\"﻿",
        "type": "appreciation",
        "contentPosition": "none",
        "commentId": "t40"
    }, {
        "userName": "SP",
        "time": -1,
        "text": "its simple and helpful!!!!! keep it up buddy",
        "type": "appreciation",
        "contentPosition": "none",
        "commentId": "t41"
    }, {
        "userName": "AB",
        "time": 63,
        "text": "when i paste it it doesnt paste help!!!11",
        "type": "troubleshooting",
        "contentPosition": "none",
        "commentId": "t42"
    }, {
        "userName": "T",
        "time": -1,
        "text": "thank you so much - I'm really really hard at learning this photoshop stuff  and you made it very very clear and easy to understand. 10/10",
        "type": "appreciation",
        "contentPosition": "none",
        "commentId": "t43"
    }, {
        "userName": "T",
        "time": 70,
        "text": "One question: I put one photo on top of another but when I did that it took  the color out of the image? What did I do wrong?",
        "type": "troubleshooting",
        "contentPosition": "none",
        "commentId": "t44"
    }, {
        "userName": "NF",
        "time": 209,
        "text": "Hey i have a question :3 i just started using photoshop but its the trail. is it possible that not all the tools are available? when you painted her face black i could not paint my photo ( the mask layer ) can you help me? :3????",
        "type": "troubleshooting",
        "contentPosition": "none",
        "commentId": "t45"
    }, {
        "userName": "H",
        "time": 209,
        "text": "No the trial version is complete and works just the same.  There has to be a missed step or an added one. If you make sure your mask layer is selected and you are using black as well your opacity of the brush is 100 it will work in all versions.?",
        "type": "suggestion",
        "contentPosition": "none",
        "commentId": "t46"
    }, {
        "userName": "NP",
        "time": -1,
        "text": "great work man !! a total thumbs up (y)",
        "type": "appreciation",
        "contentPosition": "none",
        "commentId": "t47"
    }, {
        "userName": "D",
        "time": -1,
        "text": "name of the program please?",
        "type": "question",
        "contentPosition": "none",
        "commentId": "t48"
    }, {
        "userName": "DZ",
        "time": -1,
        "text": "i have a question  how do i transfer that ps picture into a picture  I need it to be a diffrient program like Windos Photo Viewer",
        "type": "question",
        "contentPosition": "none",
        "commentId": "t49"
    }, {
        "userName": "K",
        "time": -1,
        "text": "Very good tutorial!",
        "type": "appreciation",
        "contentPosition": "none",
        "commentId": "t50"
    }, {
        "userName": "BC",
        "time": -1,
        "text": "Great little tutorial, easy to follow, nice one!!!",
        "type": "appreciation",
        "contentPosition": "none",
        "commentId": "t51"
    }, {
        "userName": "V",
        "time": 70,
        "text": "It doesn't add as a new layer,it ads into the furst one and screws up the  colors.",
        "type": "troubleshooting",
        "contentPosition": "none",
        "commentId": "t52"
    }, {
        "userName": "M",
        "time": -1,
        "text": "This Was A Very Great Tutorial. Thank you. i Just Started Using PhotoShop And I Had No Clue To What I Was Doing. LOL﻿",
        "type": "appreciation",
        "contentPosition": "none",
        "commentId": "t53"
    }, {
        "userName": "JB",
        "time": -1,
        "text": "Thanks ur Awesome!!! when i was starting is was like *dumbface* and now i  am a 10000% better in pshopping Thanks!!!!!!! I subbed and i am gonna watch  your other vids!!!!!﻿",
        "type": "appreciation",
        "contentPosition": "none",
        "commentId": "t54"
    }, {
        "userName": "KO",
        "time": 117,
        "text": "after copy pasting all I having in this step is a black box instead of the picture. why is this happening? any idea?",
        "type": "troubleshooting",
        "contentPosition": "none",
        "commentId": "t55"
    }, {
        "userName": "RA",
        "time": -1,
        "text": "Lovely thanks a lot :) you sound very clear :)",
        "type": "appreciation",
        "contentPosition": "none",
        "commentId": "t56"
    }, {
        "userName": "MM",
        "time": -1,
        "text": "You saved my life thanks a bunch",
        "type": "appreciation",
        "contentPosition": "none",
        "commentId": "t57"
    }, {
        "userName": "KC",
        "time": -1,
        "text": "Thank you! :)",
        "type": "appreciation",
        "contentPosition": "none",
        "commentId": "t58"
    }, {
        "userName": "DA",
        "time": -1,
        "text": "to much options but thanks and how can i do it online? please help me on  that",
        "type": "question",
        "contentPosition": "none",
        "commentId": "t59"
    }, {
        "userName": "T",
        "time": -1,
        "text": "Thx alote dude and u sound like seth rogen :D to be honest other tutoriol  did nt even helped me thx",
        "type": "appreciation",
        "contentPosition": "none",
        "commentId": "t60"
    }, {
        "userName": "DCC",
        "time": -1,
        "text": "thanks this is awesome",
        "type": "appreciation",
        "contentPosition": "none",
        "commentId": "t61"
    }, {
        "userName": "MH",
        "time": -1,
        "text": "very useful and easy to follow thankyou",
        "type": "appreciation",
        "contentPosition": "none",
        "commentId": "t62"
    }, {
        "userName": "JC",
        "time": -1,
        "text": "I really like your tutorials!  You talk slowly enough and have a kind voice  that is easy to listen to.  So many talk fast and forget to mention things  you need to know.  THANK YOU.  I hope you make more videos...﻿",
        "type": "appreciation",
        "contentPosition": "none",
        "commentId": "t63"
    }, {
        "userName": "LJ",
        "time": -1,
        "text": "Hello- I am using photoshop 7.0, how do I remove the background from the photo and replace it with a texture...? I am so confused- I have the 2 photo's but I don't know where the layer mask is... I am so confused. Help???",
        "type": "troubleshooting",
        "contentPosition": "none",
        "commentId": "t64"
    }, {
        "userName": "GC",
        "time": -1,
        "text": "I want to put 4/5/6/7 ecc pics one near to the other but with paint their  body parts are under the white background of the other one. Can you make a  video or link me a video for this particular problem?﻿",
        "type": "question",
        "contentPosition": "none",
        "commentId": "t65"
    }, {
        "userName": "EW",
        "time": 212,
        "text": "It wont let me paint over the mask layer can anyone tell me why this is happening i got the picture from google and just startedphotoshop yesterday so i dont know alot plz help me someone",
        "type": "troubleshooting",
        "contentPosition": "none",
        "commentId": "t66"
    }, {
        "userName": "GB",
        "time": -1,
        "text": "whats the name of the program or the site? coes theres like millions of  them on the web!!﻿",
        "type": "question",
        "contentPosition": "none",
        "commentId": "t67"
    }, {
        "userName": "DY",
        "time": 212,
        "text": "i am a beginner i like your tutorial but i have a problem it seems like i  cant paint on the layer after i select add layer mask WHY ? and what should  i do?",
        "type": "troubleshooting",
        "contentPosition": "none",
        "commentId": "t68"
    }, {
        "userName": "TP",
        "time": 230,
        "text": "I'm having a problem.So i go to the layer and choose the brush tool but  when i try to paint,the backround image will start painting.What i mean is  instead of black it will come out as my backround image.plz help!",
        "type": "troubleshooting",
        "contentPosition": "none",
        "commentId": "t69"
    }, {
        "userName": "DT",
        "time": -1,
        "text": "Thank Youuuu, btw i want those eye images, can you give me that image link?",
        "type": "question",
        "contentPosition": "none",
        "commentId": "t70"
    }, {
        "userName": "NB",
        "time": 118,
        "text": "What happens when this does not work as it just give me a blank box.",
        "type": "troubleshooting",
        "contentPosition": "none",
        "commentId": "t71"
    }, {
        "userName": "CB",
        "time": 197,
        "text": "It says\" Could not complete your request because the smart object is not directly editable.\"",
        "type": "troubleshooting",
        "contentPosition": "none",
        "commentId": "t72"
    }, {
        "userName": "XS",
        "time": -1,
        "text": "Hello Mike, I would love it if you could post a video on this problem I'm  having... you see, I have the picture, with a word (The word is a layer I  added, not a part of the image it-self) in it and I want to put a image  behind the word but the image covers over the word, and I don't know how to  put it behind it, can you help me please?",
        "type": "question",
        "contentPosition": "none",
        "commentId": "t73"
    }, {
        "userName": "0",
        "time": 210,
        "text": "Hi, I'm having a problem with this.  I managed to do this succesfully for 1 picture, when I tried doing it for a  new one on another pile of layers, I simply see myself going over the  picture with the brush, it does nothing, when I choose a pen, it simply  gums the picture away.  I double checked eveything, I did it the same way as for the first one.",
        "type": "troubleshooting",
        "contentPosition": "none",
        "commentId": "t74"
    },

    {
        "userName": "B",
        "time": -1,
        "text": "hey. I saw couple of you tutorials and they are really good. But I have  task in PS I cannot handle. I want to replace one object of some shape and  form with another object and I want it in same shape and form. Example: I  have picture of my friend with flag around his neck and on shoulders in  pose. so flag is curved, wavy and shady. Now I want to replace it with  other flag, but I want it to keep form of the old flag is this even  possible? If anyone can help or send link to the proper video I will  appreciate it. T.Hanks",
        "type": "question",
        "contentPosition": "none",
        "commentId": "t75"
    }, {
        "userName": "H",
        "time": 209,
        "text": "if you paint black on the mask you want the background to come through.  Once you have done that click CNTRL I or Comand I on a mac.That is the shortcut for Invert see if that helps you.",
        "type": "troubleshooting",
        "contentPosition": "none",
        "commentId": "t76"
    }, {
        "userName": "G",
        "time": 62,
        "text": "when i copy paste the picture i need, the opacity is really low ?although it says 100%. HELP????",
        "type": "troubleshooting",
        "contentPosition": "none",
        "commentId": "t77"
    }, {
        "userName": "H",
        "time": 62,
        "text": "Okay instead of copy paste try to drag the second image from the folder it's in right on top of the first image which is already open in photoshop.?",
        "type": "troubleshooting",
        "contentPosition": "none",
        "commentId": "t78"
    }, {
        "userName": "0",
        "time": 314,
        "text": "Hi, I'm having a problem with this. The brush option is not working for CS3! Is their any way to make the brush work?",
        "type": "troubleshooting",
        "contentPosition": "none",
        "commentId": "t79"
    }, {
        "userName": "H",
        "time": 214,
        "text": "If you see your paint strokes actually showing up on the image then you need to make sure you have the layer mask selected.  On the layer you are painting on you should see a small thumbnail of the image and to the right of that a small thumbnail of the mask which will either be all white or all black. Make sure you click directly on the mask thumbnail and then paint.?",
        "type": "troubleshooting",
        "contentPosition": "none",
        "commentId": "t80"
    }, {
        "userName": "XS",
        "time": -1,
        "text": "Hello Mike, I would love it if you could post a video on this problem I'm having... you see, I have the picture, with a word (The word is a layer I added, not a part of the image it-self) in it and I want to put a image behind the word but the image covers over the word, and I don't know how to put it behind it, can you help me please?",
        "type": "question",
        "contentPosition": "none",
        "commentId": "t81"
    },

    {
        "userName": "U",
        "time": -1,
        "text": "Here is another good tutorial on image blending: https://www.youtube.com/watch?v=A8sOF_4dwDM",
        "type": "link",
        "contentPosition": "none",
        "commentId": "t82"
    }, {
        "userName": "N",
        "time": -1,
        "text": " I found this tutorial also helpful  https://www.youtube.com/watch?v=StBOo5RsHds",
        "type": "link",
        "contentPosition": "none",
        "commentId": "t83"
    }, {
        "userName": "T",
        "time": 189,
        "text": " you can use Ctrl+Alt+J to add new layer instead of clicking the menu.",
        "type": "suggestion",
        "contentPosition": "none",
        "commentId": "t84"
    }, {
        "userName": "D",
        "time": 81,
        "text": "for transform tool Ctrl+T is a good shortcut. I regularly use it.",
        "type": "suggestion",
        "contentPosition": "none",
        "commentId": "t85"
    },

    {
        "userName": "S",
        "time": 189,
        "text": "Where is the add layer button in adobe photoshop lightroom version 5? I could not find it.",
        "type": "question",
        "contentPosition": "none",
        "commentId": "t86"
    }, {
        "userName": "T",
        "time": 189,
        "text": "It is very difficult to create new layer in adobe photoshop lightroom. use any version of photoshop instead of lightroom ",
        "type": "question",
        "contentPosition": "none",
        "commentId": "t87"
    }, {
        "userName": "T",
        "time": 215,
        "text": "I found it good practice to brush with around the edge of the photo that you are going to blend.",
        "type": "suggestion",
        "contentPosition": "none",
        "commentId": "t89"
    }, {
        "userName": "H",
        "time": 217,
        "text": "Make sure that the brush is always soft otherwise there will be some hard border.",
        "type": "suggestion",
        "contentPosition": "none",
        "commentId": "t90"
    }, {
        "userName": "D",
        "time": 217,
        "text": "What is the shortcut for bringing the brush pallet? I did not get it.",
        "type": "question",
        "contentPosition": "none",
        "commentId": "t91"
    }, {
        "userName": "H",
        "time": 217,
        "text": "please do Ctrl-Click in Image window. that would open up the brush pallet.",
        "type": "question",
        "contentPosition": "none",
        "commentId": "t92"
    }, {
        "userName": "SP",
        "time": 271,
        "text": "make sure to lower the opacity. otherwise the result won't be that good",
        "type": "suggestion",
        "contentPosition": "none",
        "commentId": "t93"
    }, {
        "userName": "Sp",
        "time": 294,
        "text": "I could not find the move tool please help!!",
        "type": "troubleshooting",
        "contentPosition": "none",
        "commentId": "t94"
    }, {
        "userName": "H",
        "time": 294,
        "text": "Where is move tool? I cant find it! I am stuck!!",
        "type": "troubleshooting",
        "contentPosition": "none",
        "commentId": "t95"
    }, {
        "userName": "JP",
        "time": 210,
        "text":"here is a link to put two pictures together in paint! https://www.youtube.com/watch?v=IgmfXLzGt2I",
        "type": "link",
        "contentPosition": "none",
        "commentId": "t96"
    }, {
        "userName": "AP",
        "time": 120,
        "text": " I think you need explain the shift key thing more clearly. I got confused!",
        "type": "suggesion",
        "contentPosition": "none",
        "commentId": "t97"
    }, {
        "userName": "H",
        "time": 209,
        "text": "I can not paint  on the face!! it says the layer is locked!! plzzzzz help!!",
        "type": "troubleshooting",
        "contentPosition": "none",
        "commentId": "t98"
    },

    {
        "userName": "H",
        "time": 63,
        "text": "When I copy paste it it does not create a new layer. Why is that happening? Can any one solve that?",
        "type": "troubleshooting",
        "contentPosition": "none",
        "commentId": "t99"
    },

    {
        "userName": "H",
        "time": 63,
        "text": "I does not let me paint in my PS CC!! why is that happening!! I am totally stuck man!!",
        "type": "troubleshooting",
        "contentPosition": "none",
        "commentId": "t100"
    }, {
        "userName": "0",
        "time": 314,
        "text": "I can not flatten the image in photoshop CC it says \"it says the layer is locked!!\" ",
        "type": "troubleshooting",
        "contentPosition": "none",
        "commentId": "t101"
    },

    {
        "userName": "J",
        "time": 314,
        "text": "Why I can not unlock the layer here? it is always greyed out! this is very very frustrating!! anyone here?",
        "type": "troubleshooting",
        "contentPosition": "none",
        "commentId": "t102"
    },

    {
        "userName": "M",
        "time": 231,
        "text": "Why my photoshop is not allowing me to use the brush? I have tried many things not working for me in this step. Someone care to listen to me? hlppp",
        "type": "troubleshooting",
        "contentPosition": "none",
        "commentId": "t103"
    },

    {
        "userName": "UU",
        "time": 204,
        "text": "The brush tool is not allowing me to paint the photo! why the hell is that happening!! solution plz!",
        "type": "troubleshooting",
        "contentPosition": "none",
        "commentId": "t104"
    },


    {
        "userName": "I",
        "time": 204,
        "text": "The brush is not good enough to paint in my PS CC!! it's kinda creating a blurry image! Why is that happening??!! I am stuck :(",
        "type": "troubleshooting",
        "contentPosition": "none",
        "commentId": "t105"
    },

    {
        "userName": "L",
        "time": 204,
        "text": "When I try to paint with the opacity in photoshop CC automatically changes. Why it is changing. Because of it I am not getting a good output. Care to solve the problem anyone??",
        "type": "troubleshooting",
        "contentPosition": "none",
        "commentId": "t106"
    },


    {
        "userName": "EE",
        "time": 204,
        "text": "When I was working with photoshop CC I found it helpful to check the opacity before starting the task. So that it does not accidently changes!",
        "type": "suggestion",
        "contentPosition": "none",
        "commentId": "t107"
    },


    {
        "userName": "FF",
        "time": 273,
        "text": "In photoshop elements 2011 it is difficult to control the opacity option. I would suggest to be careful when you are using brush.",
        "type": "suggestion",
        "contentPosition": "none",
        "commentId": "t107"
    },


    {
        "userName": "GG",
        "time": 219,
        "text": "Photoshop elements dont have this kind brush pallet. For better brush I would recommend to google!",
        "type": "suggestion",
        "contentPosition": "none",
        "commentId": "t108"
    },


    {
        "userName": "FF",
        "time": 219,
        "text": "I have a suggestion! Photoshop CC version has lots of different brushes! user those! I got beautiful output!!",
        "type": "suggestion",
        "contentPosition": "none",
        "commentId": "t109"
    },


    {
        "userName": "SM",
        "time": 210,
        "text": "If you are using phothsop CS3 then use a medium hard brush. the output result is really nice!!",
        "type": "suggestion",
        "contentPosition": "none",
        "commentId": "t110"
    },


    {
        "userName": "ST",
        "time": 315,
        "text": "Sometimes there are problems with creating layer. In that case sometimes you need to restart photoshop.",
        "type": "suggestion",
        "contentPosition": "none",
        "commentId": "t111"
    },

    {
        "userName": "LJ",
        "time": 172,
        "text": "Transfrom tool is bit different in PS elements. Sometimes it does not work properly. in many cases I needed to restart my PS! ",
        "type": "suggestion",
        "contentPosition": "none",
        "commentId": "t112"
    },


    {
        "userName": "99",
        "time": 217,
        "text": "I am trying to do this thing in gimp. I was able to everything but got stuck in this step. I am really stuck :'(",
        "type": "troubleshooting",
        "contentPosition": "none",
        "commentId": "t113"
    },


    {
        "userName": "QW",
        "time": 217,
        "text": "I have tried various versions of PS but nothing works!! why!! whenever I come to this step my PS crashes!! gives some kind hexcode error! I have no clue!! Why is that error!!WHY!!!! plzzzzz someone shed some light!! I have an assignment to submit",
        "type": "troubleshooting",
        "contentPosition": "none",
        "commentId": "t114"
    },


    {
        "userName": "KSS",
        "time": -1,
        "text": "I am trying to do this in aperture in mac. but no luck found! All I getting is aperture shutting down! why why!! someone to help?",
        "type": "troubleshooting",
        "contentPosition": "none",
        "commentId": "t115"
    },


    {
        "userName": "OP",
        "time": -1,
        "text": "Anyone here in corel paintshop? I am getting blue screen after openning one pic!! need help plz!",
        "type": "troubleshooting",
        "contentPosition": "none",
        "commentId": "t116"
    }




]
